padc/cli/__init__.py
padc/cli/__main__.py
padc/cli/cli.py
padc/cli/users.py
padc/cli/users_utils.py
padc/client/__init__.py
padc/client/client.py
padc/client/error_handler.py
padc/client/state.py
padc/config/logging_settings.ini
padc/logger/__init__.py
padc/logger/setup_log.py
padc/msad/__init__.py
padc/msad/ad_error_handler.py
padc/msad/msad.py
padc-0.3.dist-info/LICENSE
padc-0.3.dist-info/METADATA
padc-0.3.dist-info/WHEEL
padc-0.3.dist-info/entry_points.txt
padc-0.3.dist-info/top_level.txt
padc-0.3.dist-info/RECORD
