Metadata-Version: 2.1
Name: padc
Version: 0.3
Summary: python active directory cli using python-ldap lib to manage ad servers
Home-page: https://github.com/Fabiokleis/p_ad
Author: Fabio Kleis
Author-email: fabiohkrc@gmail.com
License: MIT License
License-File: LICENSE
Requires-Dist: future (==0.18.3)
Requires-Dist: pyad (==0.6.0)
Requires-Dist: pyasn1 (==0.4.8)
Requires-Dist: pyasn1-modules (==0.2.8)
Requires-Dist: python-dotenv (==0.21.1)
Requires-Dist: python-ldap (==3.4.3)
Requires-Dist: click (==8.1.3)
Requires-Dist: colorama (==0.4.6)
Requires-Dist: commonmark (==0.9.1)
Requires-Dist: Pygments (==2.14.0)
Requires-Dist: rich (==12.6.0)
Requires-Dist: shellingham (==1.5.0.post1)
Requires-Dist: typer (==0.7.0)
